syntho_hive/__init__.py
syntho_hive/connectors/__init__.py
syntho_hive/connectors/sampling.py
syntho_hive/connectors/spark_io.py
syntho_hive/core/__init__.py
syntho_hive/core/data/__init__.py
syntho_hive/core/data/transformer.py
syntho_hive/core/models/__init__.py
syntho_hive/core/models/base.py
syntho_hive/core/models/ctgan.py
syntho_hive/core/models/layers.py
syntho_hive/interface/__init__.py
syntho_hive/interface/config.py
syntho_hive/interface/synthesizer.py
syntho_hive/privacy/__init__.py
syntho_hive/privacy/faker_contextual.py
syntho_hive/privacy/sanitizer.py
syntho_hive/relational/__init__.py
syntho_hive/relational/graph.py
syntho_hive/relational/linkage.py
syntho_hive/relational/orchestrator.py
syntho_hive/tests/test_interface.py
syntho_hive/tests/test_relational.py
syntho_hive/tests/test_validation.py
syntho_hive/validation/__init__.py
syntho_hive/validation/report_generator.py
syntho_hive/validation/statistical.py
synthohive-1.2.3.dist-info/licenses/LICENSE
synthohive-1.2.3.dist-info/METADATA
synthohive-1.2.3.dist-info/WHEEL
synthohive-1.2.3.dist-info/top_level.txt
synthohive-1.2.3.dist-info/RECORD
