Metadata-Version: 2.4
Name: synthohive
Version: 1.2.3
Summary: Production Synthetic Data Engine with Relational Integrity
Author-email: SynthoHive Team <ardada2468@gmail.com>
License: MIT License
Classifier: Programming Language :: Python :: 3
Classifier: Operating System :: OS Independent
Requires-Python: >=3.9
License-File: LICENSE
Requires-Dist: numpy>=1.21.0
Requires-Dist: pandas>=1.3.0
Requires-Dist: torch>=1.10.0
Requires-Dist: pyspark>=3.2.0
Requires-Dist: pydantic>=2.0.0
Requires-Dist: scipy>=1.7.0
Requires-Dist: scikit-learn>=1.0.0
Requires-Dist: faker>=13.0.0
Requires-Dist: delta-spark>=2.0.0
Requires-Dist: structlog>=21.1.0
Requires-Dist: pyarrow>=8.0.0
Provides-Extra: dev
Requires-Dist: pytest>=7.0.0; extra == "dev"
Requires-Dist: black; extra == "dev"
Requires-Dist: flake8; extra == "dev"
Requires-Dist: mypy; extra == "dev"
Provides-Extra: docs
Requires-Dist: mkdocs>=1.6.0; extra == "docs"
Requires-Dist: mkdocs-material>=9.5.0; extra == "docs"
Requires-Dist: mkdocstrings[python]>=0.25.0; extra == "docs"
Requires-Dist: mkdocs-section-index>=0.3.8; extra == "docs"
Requires-Dist: mkdocs-autorefs>=0.5.0; extra == "docs"
Requires-Dist: mkdocs-literate-nav>=0.6.0; extra == "docs"
Requires-Dist: mkdocs-gen-files>=0.5.0; extra == "docs"
Requires-Dist: mkdocs-git-revision-date-localized-plugin>=1.2.0; extra == "docs"
Dynamic: license-file
